streamlit_plotly_events_retro/__init__.py
streamlit_plotly_events_retro/frontend/build/asset-manifest.json
streamlit_plotly_events_retro/frontend/build/index.html
streamlit_plotly_events_retro/frontend/build/precache-manifest.af763285147795fb762b3911f52874eb.js
streamlit_plotly_events_retro/frontend/build/service-worker.js
streamlit_plotly_events_retro/frontend/build/static/js/2.02ea19d3.chunk.js
streamlit_plotly_events_retro/frontend/build/static/js/2.02ea19d3.chunk.js.LICENSE.txt
streamlit_plotly_events_retro/frontend/build/static/js/2.02ea19d3.chunk.js.map
streamlit_plotly_events_retro/frontend/build/static/js/main.d2c5e4b3.chunk.js
streamlit_plotly_events_retro/frontend/build/static/js/main.d2c5e4b3.chunk.js.map
streamlit_plotly_events_retro/frontend/build/static/js/runtime-main.44d30fc2.js
streamlit_plotly_events_retro/frontend/build/static/js/runtime-main.44d30fc2.js.map
streamlit_plotly_events_retro-0.0.8.dist-info/LICENSE
streamlit_plotly_events_retro-0.0.8.dist-info/METADATA
streamlit_plotly_events_retro-0.0.8.dist-info/WHEEL
streamlit_plotly_events_retro-0.0.8.dist-info/top_level.txt
streamlit_plotly_events_retro-0.0.8.dist-info/RECORD
