Metadata-Version: 2.1
Name: streamlit-plotly-events-retro
Version: 0.0.8
Summary: Plotly chart component for Streamlit that also allows for events to bubble back up to Streamlit.
Home-page: https://github.com/null-jones/streamlit-plotly-events
Author: Ellie Jones
Author-email: ellie@altaml.com
License: UNKNOWN
Platform: UNKNOWN
Requires-Python: >=3.6
Requires-Dist: streamlit (>=0.63)
Requires-Dist: plotly (>=4.14.3)
